IS2view/__init__.py
IS2view/_version.py
IS2view/api.py
IS2view/convert.py
IS2view/io.py
IS2view/tools.py
IS2view/utilities.py
IS2view/version.py
IS2view-0.1.1.dist-info/LICENSE
IS2view-0.1.1.dist-info/METADATA
IS2view-0.1.1.dist-info/WHEEL
IS2view-0.1.1.dist-info/top_level.txt
IS2view-0.1.1.dist-info/RECORD
