Metadata-Version: 2.1
Name: IS2view
Version: 0.1.1
Summary: Interactive visualization and data extraction tool for the ICESat-2 ATL14/15 Gridded Land Ice Height Products
Author: Tyler Sutterley, Ben Smith
Author-email: tsutterl@uw.edu
Maintainer: IS2view contributors
License: MIT License
Project-URL: Homepage, https://is2view.readthedocs.io
Project-URL: Documentation, https://is2view.readthedocs.io
Project-URL: Repository, https://github.com/tsutterley/IS2view
Project-URL: Issues, https://github.com/tsutterley/IS2view/issues
Keywords: ICESat-2,elevation,digital elevation models,ipython,jupyter,graphics
Classifier: Development Status :: 3 - Alpha
Classifier: Intended Audience :: Science/Research
Classifier: License :: OSI Approved :: MIT License
Classifier: Operating System :: OS Independent
Classifier: Programming Language :: Python :: 3
Classifier: Programming Language :: Python :: 3.6
Classifier: Programming Language :: Python :: 3.7
Classifier: Programming Language :: Python :: 3.8
Classifier: Programming Language :: Python :: 3.9
Classifier: Programming Language :: Python :: 3.10
Classifier: Programming Language :: Python :: 3.11
Classifier: Programming Language :: Python :: 3.12
Classifier: Topic :: Scientific/Engineering :: Physics
Requires-Python: ~=3.6
License-File: LICENSE
Requires-Dist: h5netcdf
Requires-Dist: ipyleaflet
Requires-Dist: matplotlib
Requires-Dist: numpy
Requires-Dist: rioxarray
Requires-Dist: setuptools_scm
Requires-Dist: xarray
Provides-Extra: doc
Requires-Dist: docutils; extra == "doc"
Requires-Dist: graphviz; extra == "doc"
Requires-Dist: ipywidgets; extra == "doc"
Requires-Dist: notebook; extra == "doc"
Requires-Dist: numpydoc; extra == "doc"
Requires-Dist: sphinx; extra == "doc"
Requires-Dist: sphinx-argparse>=0.4; extra == "doc"
Requires-Dist: sphinx_rtd_theme; extra == "doc"
Provides-Extra: all
Requires-Dist: boto3; extra == "all"
Requires-Dist: bottleneck; extra == "all"
Requires-Dist: dask; extra == "all"
Requires-Dist: geopandas; extra == "all"
Requires-Dist: ipywidgets; extra == "all"
Requires-Dist: notebook; extra == "all"
Requires-Dist: owslib; extra == "all"
Requires-Dist: s3fs; extra == "all"
Requires-Dist: xyzservices; extra == "all"
Requires-Dist: zarr; extra == "all"
Provides-Extra: dev
Requires-Dist: flake8; extra == "dev"
Requires-Dist: pytest>=4.6; extra == "dev"
Requires-Dist: pytest-cov; extra == "dev"
